citylex.py
citylex_pb2.py
citylex-0.1.15.dist-info/LICENSE.txt
citylex-0.1.15.dist-info/METADATA
citylex-0.1.15.dist-info/WHEEL
citylex-0.1.15.dist-info/entry_points.txt
citylex-0.1.15.dist-info/top_level.txt
citylex-0.1.15.dist-info/RECORD
