Metadata-Version: 2.1
Name: citylex
Version: 0.1.15
Summary: Builds a multi-source English lexicon
Author: Kyle Gorman
Author-email: kylebgorman@gmail.com
License: Apache 2.0
Project-URL: homepage, https://github.com/kylebgorman/citylex
Keywords: computational linguistics,morphology,natural language processing,phonology,phonetics,speech,language
Classifier: Programming Language :: Python :: 3.8
Classifier: Programming Language :: Python :: 3.9
Classifier: Programming Language :: Python :: 3.10
Classifier: Programming Language :: Python :: 3.11
Classifier: Programming Language :: Python :: 3.12
Classifier: Development Status :: 4 - Beta
Classifier: Environment :: Console
Classifier: License :: OSI Approved :: Apache Software License
Classifier: Operating System :: OS Independent
Classifier: Topic :: Text Processing :: Linguistic
Requires-Python: >=3.8
License-File: LICENSE.txt
Requires-Dist: pandas >=1.2.2
Requires-Dist: protobuf >=3.15.0
Requires-Dist: requests >=2.25.1
